setup.py
simplescheduler/__init__.py
simplescheduler/cli.py
simplescheduler/scheduler.py
simplescheduler/version.py
simplescheduler.egg-info/PKG-INFO
simplescheduler.egg-info/SOURCES.txt
simplescheduler.egg-info/dependency_links.txt
simplescheduler.egg-info/entry_points.txt
simplescheduler.egg-info/not-zip-safe
simplescheduler.egg-info/requires.txt
simplescheduler.egg-info/top_level.txt